lugach/__init__.py
lugach/cli/__init__.py
lugach/cli/apps/__init__.py
lugach/cli/apps/get_grades.py
lugach/cli/apps/identify_absent_students.py
lugach/cli/apps/identify_quiz_concerns.py
lugach/cli/apps/modify_attendance.py
lugach/cli/apps/modify_due_dates.py
lugach/cli/apps/modify_time_limits.py
lugach/cli/apps/search_student_by_name.py
lugach/cli/apps/setup.py
lugach/cli/apps/take_attendance.py
lugach/cli/entrypoint.py
lugach/cli/interactive.py
lugach/cli/utils.py
lugach/config.py
lugach/core/__init__.py
lugach/core/constants.py
lugach/core/cvutils.py
lugach/core/flutils.py
lugach/core/mappings.py
lugach/core/secrets.py
lugach/core/thutils.py
lugach/tui/__init__.py
lugach/tui/app.py
lugach/tui/app.tcss
lugach/tui/pages/__init__.py
lugach/tui/pages/setup_view/__init__.py
lugach/tui/pages/setup_view/canvas_courses_form.py
lugach/tui/pages/setup_view/canvas_credentials_form.py
lugach/tui/pages/setup_view/liberty_credentials_form.py
lugach/tui/pages/setup_view/setup_view.py
lugach/tui/pages/setup_view/top_hat_credentials_form.py
lugach/tui/pages/students_view/__init__.py
lugach/tui/pages/students_view/student_attendance_table.py
lugach/tui/pages/students_view/student_details.py
lugach/tui/pages/students_view/student_grades_table.py
lugach/tui/pages/students_view/student_info_table.py
lugach/tui/pages/students_view/students_view.py
lugach/tui/utils.py
lugach/tui/widgets/__init__.py
lugach/tui/widgets/course_select.py
lugach/tui/widgets/status_label.py
lugach/tui/widgets/students_data_table.py
lugach-0.2.1.dist-info/WHEEL
lugach-0.2.1.dist-info/entry_points.txt
lugach-0.2.1.dist-info/METADATA
lugach-0.2.1.dist-info/RECORD
