Metadata-Version: 2.3
Name: lugach
Version: 0.2.1
Summary: An application that makes Liberty University GAs' lives easier.
Requires-Dist: canvasapi>=3.3.0
Requires-Dist: click>=8.2.1
Requires-Dist: cryptography>=45.0.6
Requires-Dist: keyring>=25.6.0
Requires-Dist: playwright>=1.57.0
Requires-Dist: pyperclip>=1.11.0
Requires-Dist: python-dotenv>=1.1.1
Requires-Dist: textual>=6.11.0
Requires-Python: >=3.12
